power_daps/__init__.py
power_daps/rust/__init__.py
power_daps/rust/cargo_command.py
power_daps/rust/actions/__init__.py
power_daps/rust/actions/clean_action.py
power_daps/rust/actions/compile_action.py
power_daps/rust/actions/compile_test_action.py
power_daps/rust/actions/default_action.py
power_daps/rust/actions/deps_action.py
power_daps/rust/actions/init_action.py
power_daps/rust/actions/package_action.py
power_daps/rust/actions/run_action.py
power_daps/rust/actions/sub_action.py
power_daps/rust/actions/unit_test_action.py
power_daps/rust/templates/__init__.py
power_daps/rust/templates/init/README.md
power_daps/rust/templates/init/actions.yml
power_daps/rust/templates/init/dependencies.yml
power_daps/rust/templates/init/config/dap_config.yml
power_daps/rust/templates/init/src/PROJECT_NAME.rs
power_daps/rust/templates/init/src/lib.rs
power_daps/rust/templates/init/tests/test_PROJECT_NAME.rs
power_daps_meta_model_rust-0.0.6.dist-info/METADATA
power_daps_meta_model_rust-0.0.6.dist-info/WHEEL
power_daps_meta_model_rust-0.0.6.dist-info/entry_points.txt
power_daps_meta_model_rust-0.0.6.dist-info/top_level.txt
power_daps_meta_model_rust-0.0.6.dist-info/RECORD
